[
  {
    "标题": "女性地狱？挑战男扮女装在印度旅行 我都遭遇了什么？印度真有那么恐怖吗？",
    "链接": "https://www.bilibili.com/video/BV1mWCVBxE8W",
    "BV号": "BV1mWCVBxE8W",
    "UP主": "Meetfood觅食",
    "来源": "浏览器"
  },
  {
    "标题": "关于影视飓风近期舆情",
    "链接": "https://www.bilibili.com/video/BV16YC3BrEDz",
    "BV号": "BV16YC3BrEDz",
    "UP主": "Meetfood觅食",
    "来源": "浏览器"
  },
  {
    "标题": "新世纪十大美剧，原来过去吃得这么好",
    "链接": "https://www.bilibili.com/video/BV1YDC3BFEVZ",
    "BV号": "BV1YDC3BFEVZ",
    "UP主": "Meetfood觅食",
    "来源": "浏览器"
  },
  {
    "标题": "【巫师】赵薇的资本博弈",
    "链接": "https://www.bilibili.com/video/BV1LiypBAEAQ",
    "BV号": "BV1LiypBAEAQ",
    "UP主": "Meetfood觅食",
    "来源": "浏览器"
  },
  {
    "标题": "100秒揭秘日本自卫队真实战力",
    "链接": "https://www.bilibili.com/video/BV1zpynBPEJQ",
    "BV号": "BV1zpynBPEJQ",
    "UP主": "Meetfood觅食",
    "来源": "浏览器"
  },
  {
    "标题": "沈阳！东北美食之城！一口气50种沈阳特色美食！本地人掏心窝版！无广无滤镜保姆级美食速通攻略！",
    "链接": "https://www.bilibili.com/video/BV1zBC1BKEtd",
    "BV号": "BV1zBC1BKEtd",
    "UP主": "Meetfood觅食",
    "来源": "浏览器"
  },
  {
    "标题": "【忍唱大挑战】二十年前的“广告曲”质量有多可怕？随便一首都能吊打当今乐坛",
    "链接": "https://www.bilibili.com/video/BV12JCuBkEgu",
    "BV号": "BV12JCuBkEgu",
    "UP主": "Meetfood觅食",
    "来源": "浏览器"
  },
  {
    "标题": "路过的蚂蚁听到这歌都停不下来……",
    "链接": "https://www.bilibili.com/video/BV1tVCXBiEU6",
    "BV号": "BV1tVCXBiEU6",
    "UP主": "Meetfood觅食",
    "来源": "浏览器"
  },
  {
    "标题": "高市早苗口出狂言，小鬼子又想赌国运？",
    "链接": "https://www.bilibili.com/video/BV1EAygBTE4c",
    "BV号": "BV1EAygBTE4c",
    "UP主": "Meetfood觅食",
    "来源": "浏览器"
  },
  {
    "标题": "喜欢一个人，就送Ta去潮汕吃牛肉…",
    "链接": "https://www.bilibili.com/video/BV1s1yEB6Eh6",
    "BV号": "BV1s1yEB6Eh6",
    "UP主": "Meetfood觅食",
    "来源": "浏览器"
  },
  {
    "标题": "全球抑郁率最高的地方？我来到了凛冬秘境挪威！｜4K杜比视界",
    "链接": "https://www.bilibili.com/video/BV182CNBBEp4",
    "BV号": "BV182CNBBEp4",
    "UP主": "Meetfood觅食",
    "来源": "浏览器"
  },
  {
    "标题": "英雄联盟总决赛，他们耳机里到底在听什么？",
    "链接": "https://www.bilibili.com/video/BV1uDCrBkEiw",
    "BV号": "BV1uDCrBkEiw",
    "UP主": "Meetfood觅食",
    "来源": "浏览器"
  },
  {
    "标题": "张居正：满天风雪中，我仍不悔一生为百姓请命",
    "链接": "https://www.bilibili.com/video/BV1CFy5BREqQ",
    "BV号": "BV1CFy5BREqQ",
    "UP主": "Meetfood觅食",
    "来源": "浏览器"
  },
  {
    "标题": "南宁大排档好啊，得去啊！可以征服每一个人类！",
    "链接": "https://www.bilibili.com/video/BV1jKygBNEfo",
    "BV号": "BV1jKygBNEfo",
    "UP主": "Meetfood觅食",
    "来源": "浏览器"
  },
  {
    "标题": "特朗普和谁是苦命鸳鸯",
    "链接": "https://www.bilibili.com/video/BV1CXynBCEQB",
    "BV号": "BV1CXynBCEQB",
    "UP主": "Meetfood觅食",
    "来源": "浏览器"
  },
  {
    "标题": "台湾没事，日本就不能有事？【毒舌的南瓜】",
    "链接": "https://www.bilibili.com/video/BV1HxCXBtEt2",
    "BV号": "BV1HxCXBtEt2",
    "UP主": "Meetfood觅食",
    "来源": "浏览器"
  },
  {
    "标题": "香港电影史上首部票房破亿本土电影！ | 从香港法律角度带你细品《毒舌大状》【01】",
    "链接": "https://www.bilibili.com/video/BV1hry3BFEoX",
    "BV号": "BV1hry3BFEoX",
    "UP主": "Meetfood觅食",
    "来源": "浏览器"
  },
  {
    "标题": "80后卡车夫妻，吃住都在车上。没有选择，只有努力坚持…",
    "链接": "https://www.bilibili.com/video/BV18BCvBxERG",
    "BV号": "BV18BCvBxERG",
    "UP主": "Meetfood觅食",
    "来源": "浏览器"
  },
  {
    "标题": "这书看了有力气",
    "链接": "https://www.bilibili.com/video/BV1rPyABpEtD",
    "BV号": "BV1rPyABpEtD",
    "UP主": "Meetfood觅食",
    "来源": "浏览器"
  },
  {
    "标题": "科比主题炸鸡店！科密因为太爱科比 开了一家科比主题纪念餐厅",
    "链接": "https://www.bilibili.com/video/BV1FPycB1EvG",
    "BV号": "BV1FPycB1EvG",
    "UP主": "Meetfood觅食",
    "来源": "浏览器"
  },
  {
    "标题": "「杜比」一生被“吊打”，为何仍是标杆？",
    "链接": "https://www.bilibili.com/video/BV1FfynBzEkh",
    "BV号": "BV1FfynBzEkh",
    "UP主": "Meetfood觅食",
    "来源": "浏览器"
  },
  {
    "标题": "上班真的能和同事成为朋友吗",
    "链接": "https://www.bilibili.com/video/BV1UZCeBXEyR",
    "BV号": "BV1UZCeBXEyR",
    "UP主": "Meetfood觅食",
    "来源": "浏览器"
  },
  {
    "标题": "冬季自驾游，晚上零下7度，把房车弄的暖暖的，在赛里木湖住一晚",
    "链接": "https://www.bilibili.com/video/BV1qaCrB9EbY",
    "BV号": "BV1qaCrB9EbY",
    "UP主": "Meetfood觅食",
    "来源": "浏览器"
  },
  {
    "标题": "山雨欲来：1964年，中央为何设立文化革命五人小组？【批鬼戏·批文化部 | 风暴前夜1】",
    "链接": "https://www.bilibili.com/video/BV1JDCMBYEzU",
    "BV号": "BV1JDCMBYEzU",
    "UP主": "Meetfood觅食",
    "来源": "浏览器"
  },
  {
    "标题": "南宁夜晚觅食偶遇知心大哥，烧烤就是要人多吃着才够味！这热情打亖人，我服了！",
    "链接": "https://www.bilibili.com/video/BV14ryEBVES4",
    "BV号": "BV14ryEBVES4",
    "UP主": "Meetfood觅食",
    "来源": "浏览器"
  },
  {
    "标题": "我想这是大家很多很多年前的回忆",
    "链接": "https://www.bilibili.com/video/BV1fgC9B4ERz",
    "BV号": "BV1fgC9B4ERz",
    "UP主": "Meetfood觅食",
    "来源": "浏览器"
  },
  {
    "标题": "原来中国美景都聚集在了丽江，这里可以看遍各种地质奇迹【EP.2】",
    "链接": "https://www.bilibili.com/video/BV1CikXBoEaH",
    "BV号": "BV1CikXBoEaH",
    "UP主": "Meetfood觅食",
    "来源": "浏览器"
  },
  {
    "标题": "体育“饭圈”的毒，毒倒的是自家哥哥",
    "链接": "https://www.bilibili.com/video/BV1q4ynBhEt6",
    "BV号": "BV1q4ynBhEt6",
    "UP主": "Meetfood觅食",
    "来源": "浏览器"
  },
  {
    "标题": "我，高市早苗，就是没有错！",
    "链接": "https://www.bilibili.com/video/BV1mzCdBLE7t",
    "BV号": "BV1mzCdBLE7t",
    "UP主": "Meetfood觅食",
    "来源": "浏览器"
  },
  {
    "标题": "日本2w日元三文鱼挑战！猛吸三文鱼瀑布，到底有多爽？",
    "链接": "https://www.bilibili.com/video/BV1j3yHBhEAD",
    "BV号": "BV1j3yHBhEAD",
    "UP主": "Meetfood觅食",
    "来源": "浏览器"
  },
  {
    "标题": "大乘语法",
    "链接": "https://www.bilibili.com/video/BV1EGCMBbEfC",
    "BV号": "BV1EGCMBbEfC",
    "UP主": "Meetfood觅食",
    "来源": "浏览器"
  },
  {
    "标题": "看着不像什么正经牌子",
    "链接": "https://www.bilibili.com/video/BV1A5CtBfEmc",
    "BV号": "BV1A5CtBfEmc",
    "UP主": "Meetfood觅食",
    "来源": "浏览器"
  },
  {
    "标题": "当一个百万粉UP主从字节离职……",
    "链接": "https://www.bilibili.com/video/BV1L7C9BXESJ",
    "BV号": "BV1L7C9BXESJ",
    "UP主": "Meetfood觅食",
    "来源": "浏览器"
  },
  {
    "标题": "万亿资产被欧美冻结，俄罗斯海外资产还能要得回来吗？",
    "链接": "https://www.bilibili.com/video/BV1Y8yEBDEgW",
    "BV号": "BV1Y8yEBDEgW",
    "UP主": "Meetfood觅食",
    "来源": "浏览器"
  },
  {
    "标题": "Gemini 3 开启智能新纪元",
    "链接": "https://www.bilibili.com/video/BV17TyHBPEYd",
    "BV号": "BV17TyHBPEYd",
    "UP主": "Meetfood觅食",
    "来源": "浏览器"
  },
  {
    "标题": "鲁豫对话戴锦华：27岁经历至暗时刻，40岁不再愤怒，50岁悟了｜陈鲁豫·慢谈EP07【视频播客】",
    "链接": "https://www.bilibili.com/video/BV1MwC5BhErh",
    "BV号": "BV1MwC5BhErh",
    "UP主": "Meetfood觅食",
    "来源": "浏览器"
  },
  {
    "标题": "日本的死气，日本人民很认可",
    "链接": "https://www.bilibili.com/video/BV14yCvBHEU6",
    "BV号": "BV14yCvBHEU6",
    "UP主": "Meetfood觅食",
    "来源": "浏览器"
  },
  {
    "标题": "殖民全世界英国啥都抢，为什么就不抢菜谱？【为什么68】",
    "链接": "https://www.bilibili.com/video/BV18wy3BoEa9",
    "BV号": "BV18wy3BoEa9",
    "UP主": "Meetfood觅食",
    "来源": "浏览器"
  },
  {
    "标题": "啧，别让广东老鼠演这些",
    "链接": "https://www.bilibili.com/video/BV1ctCTB8Ec4",
    "BV号": "BV1ctCTB8Ec4",
    "UP主": "Meetfood觅食",
    "来源": "浏览器"
  },
  {
    "标题": "陈翔六点半：大小姐驾到，通通闪开",
    "链接": "https://www.bilibili.com/video/BV1bkynBnEXj",
    "BV号": "BV1bkynBnEXj",
    "UP主": "Meetfood觅食",
    "来源": "浏览器"
  },
  {
    "标题": "五年了，是时候跟大家说清楚了",
    "链接": "https://www.bilibili.com/video/BV1qECgBAE2x",
    "BV号": "BV1qECgBAE2x",
    "UP主": "Meetfood觅食",
    "来源": "浏览器"
  },
  {
    "标题": "先吃大象抓来的羊，再让大象治好我的伤！【帝国时代4】",
    "链接": "https://www.bilibili.com/video/BV1SmywBPEj9",
    "BV号": "BV1SmywBPEj9",
    "UP主": "Meetfood觅食",
    "来源": "浏览器"
  },
  {
    "标题": "台灣普發一萬元！領錢超快 該吃頓好的了 自己煮！",
    "链接": "https://www.bilibili.com/video/BV15ny5B3Esi",
    "BV号": "BV15ny5B3Esi",
    "UP主": "Meetfood觅食",
    "来源": "浏览器"
  },
  {
    "标题": "从敢死队指挥官到革命叛徒，蒋介石经历了什么？",
    "链接": "https://www.bilibili.com/video/BV1GcyVBKEYq",
    "BV号": "BV1GcyVBKEYq",
    "UP主": "Meetfood觅食",
    "来源": "浏览器"
  },
  {
    "标题": "人家秋雅结婚，你搁这又蹦又跳的！《美丽的新娘》四川方言版",
    "链接": "https://www.bilibili.com/video/BV1jQyGBGESq",
    "BV号": "BV1jQyGBGESq",
    "UP主": "Meetfood觅食",
    "来源": "浏览器"
  },
  {
    "标题": "一秒变异！夺舍6甲5头+两把满改M14，1016万撤离！",
    "链接": "https://www.bilibili.com/video/BV1hfyJBSEbz",
    "BV号": "BV1hfyJBSEbz",
    "UP主": "Meetfood觅食",
    "来源": "浏览器"
  },
  {
    "标题": "【正片】何同学×罗永浩！青年何同学的骄傲与烦恼",
    "链接": "https://www.bilibili.com/video/BV1G7yGBvEqs",
    "BV号": "BV1G7yGBvEqs",
    "UP主": "Meetfood觅食",
    "来源": "浏览器"
  },
  {
    "标题": "GDP是会骗人的 | 一口气了解GDP",
    "链接": "https://www.bilibili.com/video/BV1EjCgBeEn5",
    "BV号": "BV1EjCgBeEn5",
    "UP主": "Meetfood觅食",
    "来源": "浏览器"
  },
  {
    "标题": "满级煎鱼技能12个不为人知的细节",
    "链接": "https://www.bilibili.com/video/BV1DgCCB2E5i",
    "BV号": "BV1DgCCB2E5i",
    "UP主": "Meetfood觅食",
    "来源": "浏览器"
  },
  {
    "标题": "因意外而诞生的经典镜头！演员看着很投入，其实那是忘词了！",
    "链接": "https://www.bilibili.com/video/BV1YrCTBSEAu",
    "BV号": "BV1YrCTBSEAu",
    "UP主": "Meetfood觅食",
    "来源": "浏览器"
  },
  {
    "标题": "从夯到拉！锐评全球各国住房模式！",
    "链接": "https://www.bilibili.com/video/BV1FuCMBaE8K",
    "BV号": "BV1FuCMBaE8K",
    "UP主": "Meetfood觅食",
    "来源": "浏览器"
  },
  {
    "标题": "射击游戏凭什么能持续爆火，并且长盛不衰的？",
    "链接": "https://www.bilibili.com/video/BV1x9yVBfEii",
    "BV号": "BV1x9yVBfEii",
    "UP主": "Meetfood觅食",
    "来源": "浏览器"
  },
  {
    "标题": "大佬登场，丝滑车技恐怖如斯！结局叫人意想不到",
    "链接": "https://www.bilibili.com/video/BV1kiyHBVECn",
    "BV号": "BV1kiyHBVECn",
    "UP主": "Meetfood觅食",
    "来源": "浏览器"
  },
  {
    "标题": "【年度大视频】一口气（9小时）看完战国时代！",
    "链接": "https://www.bilibili.com/video/BV1DnCLBKEVU",
    "BV号": "BV1DnCLBKEVU",
    "UP主": "Meetfood觅食",
    "来源": "浏览器"
  },
  {
    "标题": "【墨菲】《绝命毒师》团队新作，蜂巢思维“强制幸福病毒”降临阿尔伯克基《同乐者》1-2集",
    "链接": "https://www.bilibili.com/video/BV17VCMBZEp6",
    "BV号": "BV17VCMBZEp6",
    "UP主": "Meetfood觅食",
    "来源": "浏览器"
  },
  {
    "标题": "【老鼠人行动】航天基地（绝密）60w→???w",
    "链接": "https://www.bilibili.com/video/BV1PJywBWEai",
    "BV号": "BV1PJywBWEai",
    "UP主": "Meetfood觅食",
    "来源": "浏览器"
  },
  {
    "标题": "当你的兄弟变成女人",
    "链接": "https://www.bilibili.com/video/BV1jFC3BNEsc",
    "BV号": "BV1jFC3BNEsc",
    "UP主": "Meetfood觅食",
    "来源": "浏览器"
  },
  {
    "标题": "8分钟看懂日本命脉，军事基地、能源储备、核心工厂全揭秘！",
    "链接": "https://www.bilibili.com/video/BV1PyC9BNEww",
    "BV号": "BV1PyC9BNEww",
    "UP主": "Meetfood觅食",
    "来源": "浏览器"
  },
  {
    "标题": "人造畸变霸王龙！4层楼高，一口一架直升机，毁灭整座岛【科幻Fans 布玛】《侏罗纪世界：重生》",
    "链接": "https://www.bilibili.com/video/BV11SynB1E3X",
    "BV号": "BV11SynB1E3X",
    "UP主": "Meetfood觅食",
    "来源": "浏览器"
  },
  {
    "标题": "狗知道自己是狗吗？",
    "链接": "https://www.bilibili.com/video/BV1yuCvBLEex",
    "BV号": "BV1yuCvBLEex",
    "UP主": "Meetfood觅食",
    "来源": "浏览器"
  },
  {
    "标题": "【100秒循环】弹！弹！弹！这声音很悦耳！",
    "链接": "https://www.bilibili.com/video/BV1M8yGB4EKn",
    "BV号": "BV1M8yGB4EKn",
    "UP主": "Meetfood觅食",
    "来源": "浏览器"
  },
  {
    "标题": "用AI把历史名人变成游戏boss【第九期】",
    "链接": "https://www.bilibili.com/video/BV1dGCQB7EU8",
    "BV号": "BV1dGCQB7EU8",
    "UP主": "Meetfood觅食",
    "来源": "浏览器"
  },
  {
    "标题": "新加坡：别人说我是热带美食荒漠…！？",
    "链接": "https://www.bilibili.com/video/BV1KrCgB7Ex1",
    "BV号": "BV1KrCgB7Ex1",
    "UP主": "Meetfood觅食",
    "来源": "浏览器"
  },
  {
    "标题": "一巴掌打成脑震荡，扇耳光比赛是谁想出来的？",
    "链接": "https://www.bilibili.com/video/BV1TTy3BWEV4",
    "BV号": "BV1TTy3BWEV4",
    "UP主": "Meetfood觅食",
    "来源": "浏览器"
  },
  {
    "标题": "古法烤鱼，现钓现吃～",
    "链接": "https://www.bilibili.com/video/BV1ZSyGBkESW",
    "BV号": "BV1ZSyGBkESW",
    "UP主": "Meetfood觅食",
    "来源": "浏览器"
  },
  {
    "标题": "他们到底在笑啥？！笑点高的叉出去。【十级学者详解武林外传13-1】",
    "链接": "https://www.bilibili.com/video/BV1bjCRBGEKs",
    "BV号": "BV1bjCRBGEKs",
    "UP主": "Meetfood觅食",
    "来源": "浏览器"
  },
  {
    "标题": "《星际争霸》（星海争霸）1998-2015，一个时代的完结，刀锋女王，萨尔纳迦，吉姆雷诺，攻城坦克……RTS巅峰之作，后无来者",
    "链接": "https://www.bilibili.com/video/BV1wfCUBJEMR",
    "BV号": "BV1wfCUBJEMR",
    "UP主": "Meetfood觅食",
    "来源": "浏览器"
  },
  {
    "标题": "许三多是怎么摆脱精神内耗的？低谷期如何才能破局？",
    "链接": "https://www.bilibili.com/video/BV11MCqB9ERZ",
    "BV号": "BV11MCqB9ERZ",
    "UP主": "Meetfood觅食",
    "来源": "浏览器"
  },
  {
    "标题": "在这种氛围下散步真的是种享受~",
    "链接": "https://www.bilibili.com/video/BV1caCCBYE8u",
    "BV号": "BV1caCCBYE8u",
    "UP主": "Meetfood觅食",
    "来源": "浏览器"
  },
  {
    "标题": "登山滑坠200米全部重伤，两人在勒多曼因峰展开艰难求生",
    "链接": "https://www.bilibili.com/video/BV16VCvBkEr6",
    "BV号": "BV16VCvBkEr6",
    "UP主": "Meetfood觅食",
    "来源": "浏览器"
  },
  {
    "标题": "🍎bro在日本泡温泉结果尴尬了",
    "链接": "https://www.bilibili.com/video/BV1JKCQBpEnH",
    "BV号": "BV1JKCQBpEnH",
    "UP主": "Meetfood觅食",
    "来源": "浏览器"
  },
  {
    "标题": "硬闯人均500+餐厅，只为这份焗饭！值得吗？",
    "链接": "https://www.bilibili.com/video/BV1ksCuBuErF",
    "BV号": "BV1ksCuBuErF",
    "UP主": "Meetfood觅食",
    "来源": "浏览器"
  },
  {
    "标题": "面容+层层恐惧+逃生 全新超刺激恐怖游戏《Unmourned》全流程惊悚实况",
    "链接": "https://www.bilibili.com/video/BV1fXy5BEEiL",
    "BV号": "BV1fXy5BEEiL",
    "UP主": "Meetfood觅食",
    "来源": "浏览器"
  },
  {
    "标题": "【2025·11月电脑配置推荐】爆肝一个月！教你装机不花冤枉钱！学生党直接抄作业，从2千-5万预算，共计26套台式电脑配置，小白必看攻略！电脑装机！建议收藏！",
    "链接": "https://www.bilibili.com/video/BV1FwyHBqEDz",
    "BV号": "BV1FwyHBqEDz",
    "UP主": "Meetfood觅食",
    "来源": "浏览器"
  },
  {
    "标题": "伦敦贫民窟vs顶级庄园，英国人真实居住环境是什么样的？",
    "链接": "https://www.bilibili.com/video/BV1ZrC1BPEXd",
    "BV号": "BV1ZrC1BPEXd",
    "UP主": "Meetfood觅食",
    "来源": "浏览器"
  },
  {
    "标题": "高市早苗要搞事",
    "链接": "https://www.bilibili.com/video/BV1ZoCgBKEUp",
    "BV号": "BV1ZoCgBKEUp",
    "UP主": "Meetfood觅食",
    "来源": "浏览器"
  },
  {
    "标题": "【STN快报第八季33】我被台湾人开除人籍",
    "链接": "https://www.bilibili.com/video/BV1fTCQBDESF",
    "BV号": "BV1fTCQBDESF",
    "UP主": "Meetfood觅食",
    "来源": "浏览器"
  },
  {
    "标题": "河南的胡辣汤真的好喝到爆！这顿早餐吃完整个人都舒坦了！",
    "链接": "https://www.bilibili.com/video/BV15xyEBWE7q",
    "BV号": "BV15xyEBWE7q",
    "UP主": "Meetfood觅食",
    "来源": "浏览器"
  },
  {
    "标题": "人均别墅？天价房产？普通日本人住什么样的房子？",
    "链接": "https://www.bilibili.com/video/BV19qCNByE3D",
    "BV号": "BV19qCNByE3D",
    "UP主": "Meetfood觅食",
    "来源": "浏览器"
  },
  {
    "标题": "纪录片小组摸进KK园区",
    "链接": "https://www.bilibili.com/video/BV1E6CeBKEkB",
    "BV号": "BV1E6CeBKEkB",
    "UP主": "Meetfood觅食",
    "来源": "浏览器"
  },
  {
    "标题": "96小时极限追踪！一人杀穿黑帮人贩组织！经典爽片《飓风营救》",
    "链接": "https://www.bilibili.com/video/BV1dgyHBcEQj",
    "BV号": "BV1dgyHBcEQj",
    "UP主": "Meetfood觅食",
    "来源": "浏览器"
  },
  {
    "标题": "“恩公～快来和我一起玩水呀～”",
    "链接": "https://www.bilibili.com/video/BV1CuyEBNEws",
    "BV号": "BV1CuyEBNEws",
    "UP主": "Meetfood觅食",
    "来源": "浏览器"
  },
  {
    "标题": "10元改装vs二百万元改装的赛车有多大差别？",
    "链接": "https://www.bilibili.com/video/BV1sTynB5ED1",
    "BV号": "BV1sTynB5ED1",
    "UP主": "Meetfood觅食",
    "来源": "浏览器"
  },
  {
    "标题": "她这么美怎么可能是鬼！",
    "链接": "https://www.bilibili.com/video/BV1aJyGBPEvD",
    "BV号": "BV1aJyGBPEvD",
    "UP主": "Meetfood觅食",
    "来源": "浏览器"
  },
  {
    "标题": "沈阳觅食记：超厚芝士披萨+老式麻辣烫+炸鸡排！",
    "链接": "https://www.bilibili.com/video/BV1gzynBpEdc",
    "BV号": "BV1gzynBpEdc",
    "UP主": "Meetfood觅食",
    "来源": "浏览器"
  },
  {
    "标题": "爱泼斯坦让特朗普与头号女粉决裂？！",
    "链接": "https://www.bilibili.com/video/BV19BywBgEr2",
    "BV号": "BV19BywBgEr2",
    "UP主": "Meetfood觅食",
    "来源": "浏览器"
  },
  {
    "标题": "Dory｜解锁冬天的第一顿寿喜锅与莓果热红酒！和妹妹去吃窑烤披萨｜吃香香脆脆的三明治｜一个人去咖啡店看书｜",
    "链接": "https://www.bilibili.com/video/BV117CrBPEHe",
    "BV号": "BV117CrBPEHe",
    "UP主": "Meetfood觅食",
    "来源": "浏览器"
  },
  {
    "标题": "高市早苗叫嚣出兵台海，网友弹幕刷屏：一言为定！",
    "链接": "https://www.bilibili.com/video/BV1XdCVBeECG",
    "BV号": "BV1XdCVBeECG",
    "UP主": "Meetfood觅食",
    "来源": "浏览器"
  },
  {
    "标题": "顶着轰炸写代码？我们发现了一款加沙开发者独立制作的游戏…",
    "链接": "https://www.bilibili.com/video/BV1BTC4ByErJ",
    "BV号": "BV1BTC4ByErJ",
    "UP主": "Meetfood觅食",
    "来源": "浏览器"
  },
  {
    "标题": "跟封门村一样猛！藏在海上的巨型无人村！中式恐怖天花板02！",
    "链接": "https://www.bilibili.com/video/BV1vXyHBaEbu",
    "BV号": "BV1vXyHBaEbu",
    "UP主": "Meetfood觅食",
    "来源": "浏览器"
  },
  {
    "标题": "半年13人死亡，高度城市化的日本，为什么会熊灾泛滥？",
    "链接": "https://www.bilibili.com/video/BV1SkyFBfEnq",
    "BV号": "BV1SkyFBfEnq",
    "UP主": "Meetfood觅食",
    "来源": "浏览器"
  },
  {
    "标题": "拉完了？25 个【名创优品】的电子产品，实测完之后，我懵了……",
    "链接": "https://www.bilibili.com/video/BV1M1ynBEERQ",
    "BV号": "BV1M1ynBEERQ",
    "UP主": "Meetfood觅食",
    "来源": "浏览器"
  },
  {
    "标题": "在大连花440元吃23年老店，主做附近居民生意，吃到人生肥肠！还体验了特色黑金紫胆包和海肠包子",
    "链接": "https://www.bilibili.com/video/BV1F2yGB1EK8",
    "BV号": "BV1F2yGB1EK8",
    "UP主": "Meetfood觅食",
    "来源": "浏览器"
  },
  {
    "标题": "《 英 雄 本 树 》",
    "链接": "https://www.bilibili.com/video/BV14rC9BTEAc",
    "BV号": "BV14rC9BTEAc",
    "UP主": "Meetfood觅食",
    "来源": "浏览器"
  },
  {
    "标题": "北京出租车师傅们私藏的美食街？小吃炒菜一条龙服务？",
    "链接": "https://www.bilibili.com/video/BV1Tiy5BcEDQ",
    "BV号": "BV1Tiy5BcEDQ",
    "UP主": "Meetfood觅食",
    "来源": "浏览器"
  },
  {
    "标题": "赌石大垮 39万变4万",
    "链接": "https://www.bilibili.com/video/BV1EpC2BKEtZ",
    "BV号": "BV1EpC2BKEtZ",
    "UP主": "Meetfood觅食",
    "来源": "浏览器"
  },
  {
    "标题": "【罗翔】看到路人被车撞打电话报警就要负责到底吗？",
    "链接": "https://www.bilibili.com/video/BV1uLCaByEJ2",
    "BV号": "BV1uLCaByEJ2",
    "UP主": "Meetfood觅食",
    "来源": "浏览器"
  },
  {
    "标题": "Vlog | 巴西旅行之圣保罗，这边的饺子是芝士馅的！还吃到了鱼肉炖香蕉！",
    "链接": "https://www.bilibili.com/video/BV12ACyB3EtD",
    "BV号": "BV12ACyB3EtD",
    "UP主": "Meetfood觅食",
    "来源": "浏览器"
  },
  {
    "标题": "【细讲潜伏28】斯蒂庞克多值钱？94军凭啥有钱又嚣张？【十级学者详解潜伏】",
    "链接": "https://www.bilibili.com/video/BV1giCyBUENA",
    "BV号": "BV1giCyBUENA",
    "UP主": "Meetfood觅食",
    "来源": "浏览器"
  },
  {
    "标题": "披萨店老板辱骂华人：跨国“护犊子大战”，这事儿忒解气",
    "链接": "https://www.bilibili.com/video/BV1RRyGBuE2u",
    "BV号": "BV1RRyGBuE2u",
    "UP主": "Meetfood觅食",
    "来源": "浏览器"
  }
]